omega_models/__init__.py
omega_models/models/__init__.py
omega_models/models/adaptive_abstraction_forest.py
omega_models/models/adaptive_aggressiveness_classifier.py
omega_models/models/adaptive_density_weighted_classifier.py
omega_models/models/adaptive_residual_learning_classifier.py
omega_models/models/dim_aware_forest.py
omega_models/models/directional_forest.py
omega_models/models/residual_mlp_ensemble.py
omega_models-0.3.2.dist-info/licenses/LICENSE
omega_models-0.3.2.dist-info/METADATA
omega_models-0.3.2.dist-info/WHEEL
omega_models-0.3.2.dist-info/top_level.txt
omega_models-0.3.2.dist-info/RECORD
