Metadata-Version: 2.4
Name: omega-models
Version: 0.3.2
Summary: A collection of generated machine learning algorithms
Author-email: Annika Singh <annikas@infinity.inc>
Classifier: Programming Language :: Python :: 3
Classifier: License :: OSI Approved :: MIT License
Classifier: Operating System :: OS Independent
Requires-Python: >=3.6
License-File: LICENSE
Requires-Dist: numpy<2.0
Requires-Dist: scikit-learn<1.8
Requires-Dist: scipy<1.17
Dynamic: license-file
